webapp_install_banner/urls.py
webapp_install_banner/__init__.py
webapp_install_banner/middleware.py
webapp_install_banner/models.py
webapp_install_banner/settings.py
webapp_install_banner/tests.py
webapp_install_banner/admin.py
webapp_install_banner/apps.py
webapp_install_banner/views.py
webapp_install_banner/migrations/__init__.py
webapp_install_banner/templatetags/webapp_tags.py
webapp_install_banner/templatetags/__init__.py
django_webapp_install_banner-0.1.0.dist-info/RECORD
django_webapp_install_banner-0.1.0.dist-info/METADATA
django_webapp_install_banner-0.1.0.dist-info/DESCRIPTION.rst
django_webapp_install_banner-0.1.0.dist-info/metadata.json
django_webapp_install_banner-0.1.0.dist-info/top_level.txt
django_webapp_install_banner-0.1.0.dist-info/WHEEL
