Metadata-Version: 2.0
Name: django-webapp-install-banner
Version: 0.1.0
Summary: Add web App install banner to django project
Home-page: https://bitbucket.org/ferranp/django-webapp-install-banner
Author: Ferran Pegueroles
Author-email: ferran@pegueroles.com
License: BSD
Keywords: django-webapp-install-banner
Platform: UNKNOWN
Classifier: Development Status :: 3 - Alpha
Classifier: Framework :: Django
Classifier: Framework :: Django :: 1.8
Classifier: Framework :: Django :: 1.9
Classifier: Intended Audience :: Developers
Classifier: License :: OSI Approved :: BSD License
Classifier: Natural Language :: English
Classifier: Programming Language :: Python :: 2
Classifier: Programming Language :: Python :: 2.7
Classifier: Programming Language :: Python :: 3
Classifier: Programming Language :: Python :: 3.3
Classifier: Programming Language :: Python :: 3.4
Classifier: Programming Language :: Python :: 3.5
